servicegraph/__init__.py
servicegraph/application_builder.py
servicegraph/configuration.py
servicegraph/configuration_builder.py
servicegraph/configuration_section.py
servicegraph/dependency_injection_utils.py
servicegraph/i_configuration.py
servicegraph/i_configuration_builder.py
servicegraph/i_configuration_section.py
servicegraph/py.typed
servicegraph/request_context.py
servicegraph/service_collection.py
servicegraph/service_lifetime.py
servicegraph/service_locator.py
servicegraph/service_provider.py
servicegraph/service_registration.py
servicegraph/type_hints.py
servicegraph-0.1.3.dist-info/METADATA
servicegraph-0.1.3.dist-info/WHEEL
servicegraph-0.1.3.dist-info/licenses/LICENSE
servicegraph-0.1.3.dist-info/licenses/NOTICE
servicegraph-0.1.3.dist-info/RECORD
