Metadata-Version: 2.4
Name: servicegraph
Version: 0.1.3
Summary: A lightweight dependency injection framework for Python
Project-URL: Homepage, https://github.com/servicegraph-foss
Project-URL: Documentation, https://github.com/servicegraph-foss/servicegraph-py/blob/main/README.md
Project-URL: Repository, https://github.com/servicegraph-foss/servicegraph-py.git
Project-URL: Bug Tracker, https://github.com/servicegraph-foss/servicegraph-py/issues
Project-URL: Changelog, https://github.com/servicegraph-foss/servicegraph-py/blob/main/CHANGELOG.md
Author: ServiceGraph Contributors
Maintainer: ServiceGraph Contributors
License: Apache License  
License-File: LICENSE
License-File: NOTICE
Keywords: dependency-injection,di,framework,inversion-of-control,ioc,service-container
Classifier: Development Status :: 4 - Beta
Classifier: Intended Audience :: Developers
Classifier: License :: Other/Proprietary License
Classifier: Operating System :: OS Independent
Classifier: Programming Language :: Python :: 3
Classifier: Programming Language :: Python :: 3.9
Classifier: Programming Language :: Python :: 3.10
Classifier: Programming Language :: Python :: 3.11
Classifier: Programming Language :: Python :: 3.12
Classifier: Topic :: Software Development :: Libraries :: Application Frameworks
Classifier: Topic :: Software Development :: Libraries :: Python Modules
Classifier: Typing :: Typed
Requires-Python: >=3.9
Requires-Dist: typing-extensions>=4.0.0; python_version < '3.10'
Provides-Extra: dev
Requires-Dist: black>=23.0.0; extra == 'dev'
Requires-Dist: flake8>=6.0.0; extra == 'dev'
Requires-Dist: isort>=5.12.0; extra == 'dev'
Requires-Dist: mypy>=1.0.0; extra == 'dev'
Requires-Dist: pre-commit>=3.0.0; extra == 'dev'
Requires-Dist: pytest-asyncio>=0.21.0; extra == 'dev'
Requires-Dist: pytest-cov>=4.0.0; extra == 'dev'
Requires-Dist: pytest>=7.0.0; extra == 'dev'
Provides-Extra: docs
Requires-Dist: myst-parser>=1.0.0; extra == 'docs'
Requires-Dist: sphinx-rtd-theme>=1.2.0; extra == 'docs'
Requires-Dist: sphinx>=6.0.0; extra == 'docs'
Provides-Extra: lint
Requires-Dist: black>=23.0.0; extra == 'lint'
Requires-Dist: flake8>=6.0.0; extra == 'lint'
Requires-Dist: isort>=5.12.0; extra == 'lint'
Requires-Dist: mypy>=1.0.0; extra == 'lint'
Provides-Extra: test
Requires-Dist: pytest-asyncio>=0.21.0; extra == 'test'
Requires-Dist: pytest-cov>=4.0.0; extra == 'test'
Requires-Dist: pytest>=7.0.0; extra == 'test'
